sts_credentials/__init__.py
sts_credentials/credentials/__init__.py
sts_credentials/credentials/cos.py
sts_credentials/credentials/oss.py
sts_credentials/utils/__init__.py
sts_credentials/utils/decorators.py
sts_credentials-0.0.3.dist-info/METADATA
sts_credentials-0.0.3.dist-info/WHEEL
sts_credentials-0.0.3.dist-info/licenses/LICENSE
sts_credentials-0.0.3.dist-info/RECORD
