Metadata-Version: 2.1
Name: sts-credentials
Version: 0.0.3
Summary: get sts credentials tools, use pydantic for autocompletion.
Project-URL: Homepage, https://github.com/sunfkny/sts-credentials
Author-email: sunfkny <sunfkny@gmail.com>
License-File: LICENSE
Classifier: License :: OSI Approved :: MIT License
Classifier: Operating System :: OS Independent
Classifier: Programming Language :: Python
Classifier: Programming Language :: Python :: 3
Classifier: Programming Language :: Python :: 3 :: Only
Classifier: Programming Language :: Python :: 3.7
Classifier: Programming Language :: Python :: 3.8
Classifier: Programming Language :: Python :: 3.9
Classifier: Programming Language :: Python :: 3.10
Classifier: Programming Language :: Python :: 3.11
Classifier: Topic :: Software Development
Classifier: Topic :: Utilities
Classifier: Typing :: Typed
Requires-Python: >=3.7
Requires-Dist: alibabacloud-sts20150401<2,>=1
Requires-Dist: pydantic
Requires-Dist: qcloud-python-sts<4,>=3
